ai/__init__.py
ai/assistants.py
ai/settings.py
ai/storage.py
ai/vectordb.py
ai/llm/factory.py
ai/llm/openai_chat.py
app/__init__.py
app/main.py
app/api/__init__.py
app/api/auth.py
app/api/main.py
app/api/settings.py
app/api/middleware/error_handler.py
app/api/routes/__init__.py
app/api/routes/assistants.py
app/api/routes/endpoints.py
app/api/routes/health.py
app/api/routes/status.py
app/api/routes/tools.py
app/api/routes/v1_router.py
app/components/__init__.py
app/components/chat.py
app/components/history.py
app/components/knowledge_base.py
app/components/sidebar.py
app/components/tools.py
app/config/__init__.py
app/config/ai_settings.py
app/config/settings.py
app/db/__init__.py
app/db/base.py
app/db/config.py
app/db/factory.py
app/db/init.py
app/db/memory.py
app/db/memory_storage.py
app/db/models.py
app/db/session.py
app/db/settings.py
app/db/sqlite.py
app/db/sqlite_adapter.py
app/db/storage.py
app/styles/__init__.py
app/styles/css.py
app/tools/protocol/executor.py
app/tools/protocol/models.py
app/tools/protocol/registry.py
app/tools/protocol/adapters/base.py
app/tools/protocol/adapters/python_plugin.py
app/tools/protocol/adapters/rest_api.py
app/utils/__init__.py
app/utils/session.py
examples/register_calculator.py
examples/test_calculator.py
examples/tools/calculator.py
mcp_solana/__init__.py
mcp_solana/setup.py
mcp_solana/client/__init__.py
mcp_solana/client/client.py
mcp_solana/client/contract_client.py
mcp_solana/examples/client_example.py
mcp_solana/examples/contract_example.py
mcp_solana/examples/server_example.py
mcp_solana/models/__init__.py
mcp_solana/models/protocol.py
mcp_solana/server/__init__.py
mcp_solana/server/contract_server.py
mcp_solana/server/server.py
mcp_solana/tests/test_client.py
mcp_solana/tests/test_server.py
mcp_solana/utils/__init__.py
mcp_solana/utils/contract_utils.py
mcp_solana/utils/transport.py
mseep_llm_os-0.1.2.dist-info/licenses/LICENSE
scripts/check_db.py
scripts/dev.py
scripts/init_db.py
test/test_sqlite_adapter.py
test/test_storage.py
workspace/__init__.py
mseep_llm_os-0.1.2.dist-info/METADATA
mseep_llm_os-0.1.2.dist-info/WHEEL
mseep_llm_os-0.1.2.dist-info/top_level.txt
mseep_llm_os-0.1.2.dist-info/RECORD
